{
	"questions": [
		{
			"id": 1,
			"text": "Что вам интересно?",
			"options": [
				"Программирование",
				"Музыка",
				"Фильмы",
				"Путешествия",
				"Чтение",
				"Инженерное дело",
				"Искусство",
				"Иностранные языки"
			],
			"answer": null
		},
		{
			"id": 2,
			"text": "Какие предметы вам нравится изучать?",
			"options": [
				"Математика",
				"Физика",
				"Химия",
				"Биология",
				"Информатика",
				"Иностранные языки",
				"История",
				"География"
			],
			"answer": null
		},
		{
			"id": 3,
			"text": "Какой у вас опыт работы?",
			"options": [
				"Отсутствует",
				"Стажировка в технологической компании",
				"Работа в розничном магазине летом",
				"Волонтерство в некоммерческой организации",
				"Работа репетитором",
				"Обучение в строительном ученичестве",
				"Фрилансерская работа в качестве графического дизайнера",
				"Участие в студенческой программе работы в университетской лаборатории"
			],
			"answer": null
		},
		{
			"id": 4,
			"text": "Каковы ваши долгосрочные карьерные цели?",
			"options": [
				"Открыть свой бизнес",
				"Работать в Технологическом гиганте, таком как Google или Apple",
				"Стать профессором или исследователем",
				"Работать в творческой сфере, например, в кино или музыке",
				"Путешествовать по всему миру и работать удаленно",
				"Сделать позитивные изменения в мире через социальное предпринимательство",
				"Иметь стабильную работу с высокой заработной платой и социальными льготами",
				"Иметь гибкую и удовлетворительную карьеру"
			],
			"answer": null
		}
	]
}
